<vector xmlns:android="http://schemas.android.com/apk/res/android"
    xmlns:aapt="http://schemas.android.com/aapt"
    android:width="32dp"
    android:height="32dp"
    android:viewportWidth="32"
    android:viewportHeight="32">
  <path
      android:pathData="M15.8212,11.106C15.6508,11.7678 15.0721,12.2615 14.3881,12.6035C12.4492,13.2744 10.9176,13.9197 9.6503,14.5462C8.5284,15.1008 8.5392,16.8535 9.6648,17.4007C10.9799,18.04 12.631,18.6532 14.4648,19.3801C14.9579,19.5756 15.6547,20.1278 15.8281,20.8066C16.3626,22.8983 17.0898,25.1126 17.8906,27.1568C18.5122,28.7436 20.049,28.7424 20.6737,27.1568C21.4846,25.0984 22.1006,22.875 22.7959,20.7596C22.9623,20.1064 23.455,19.5899 24.0903,19.3649C25.8073,18.7566 27.4624,18.0702 28.8115,17.476C30.0714,16.9211 30.0974,15.1195 28.8533,14.5301C27.5247,13.9007 25.8721,13.1719 24.082,12.5214C23.452,12.2925 22.9673,11.8093 22.7433,11.1235C21.9888,8.8125 21.5107,6.8533 20.7091,4.8186C20.0844,3.233 18.4445,3.2818 17.8198,4.8674C17.0212,6.8946 16.4637,8.9123 15.8212,11.106Z">
    <aapt:attr name="android:fillColor">
      <gradient 
          android:startY="11.2713"
          android:startX="26.1287"
          android:endY="22.9314"
          android:endX="15.0524"
          android:type="linear">
        <item android:offset="0" android:color="#FFFFCF5A"/>
        <item android:offset="1" android:color="#FFFEA254"/>
      </gradient>
    </aapt:attr>
  </path>
  <path
      android:pathData="M15.8212,11.106C15.6508,11.7678 15.0721,12.2615 14.3881,12.6035C12.4492,13.2744 10.9176,13.9197 9.6503,14.5462C8.5284,15.1008 8.5392,16.8535 9.6648,17.4007C10.9799,18.04 12.631,18.6532 14.4648,19.3801C14.9579,19.5756 15.6547,20.1278 15.8281,20.8066C16.3626,22.8983 17.0898,25.1126 17.8906,27.1568C18.5122,28.7436 20.049,28.7424 20.6737,27.1568C21.4846,25.0984 22.1006,22.875 22.7959,20.7596C22.9623,20.1064 23.455,19.5899 24.0903,19.3649C25.8073,18.7566 27.4624,18.0702 28.8115,17.476C30.0714,16.9211 30.0974,15.1195 28.8533,14.5301C27.5247,13.9007 25.8721,13.1719 24.082,12.5214C23.452,12.2925 22.9673,11.8093 22.7433,11.1235C21.9888,8.8125 21.5107,6.8533 20.7091,4.8186C20.0844,3.233 18.4445,3.2818 17.8198,4.8674C17.0212,6.8946 16.4637,8.9123 15.8212,11.106Z">
    <aapt:attr name="android:fillColor">
      <gradient 
          android:startY="29.2903"
          android:startX="14.7537"
          android:endY="16.5541"
          android:endX="20.7916"
          android:type="linear">
        <item android:offset="0" android:color="#FFFF886D"/>
        <item android:offset="1" android:color="#00FF886D"/>
      </gradient>
    </aapt:attr>
  </path>
  <path
      android:pathData="M7.768,5.8163C7.7132,6.0293 7.5269,6.1882 7.3068,6.2983C6.6827,6.5142 6.1898,6.7219 5.7819,6.9236C5.4208,7.1021 5.4243,7.6662 5.7865,7.8423C6.2098,8.0481 6.7413,8.2454 7.3315,8.4794C7.4902,8.5423 7.7144,8.72 7.7703,8.9385C7.9423,9.6117 8.1763,10.3244 8.4341,10.9824C8.6342,11.4931 9.1288,11.4927 9.3298,10.9824C9.5908,10.3199 9.7891,9.6042 10.0129,8.9234C10.0665,8.7132 10.225,8.5469 10.4295,8.4745C10.9821,8.2787 11.5148,8.0578 11.9491,7.8665C12.3546,7.6879 12.3629,7.1081 11.9625,6.9184C11.5349,6.7158 11.003,6.4812 10.4268,6.2719C10.224,6.1982 10.068,6.0427 9.996,5.8219C9.7531,5.0781 9.5992,4.4475 9.3412,3.7927C9.1402,3.2823 8.6124,3.298 8.4113,3.8084C8.1543,4.4608 7.9748,5.1103 7.768,5.8163Z">
    <aapt:attr name="android:fillColor">
      <gradient 
          android:startY="5.86949"
          android:startX="11.0856"
          android:endY="9.62239"
          android:endX="7.52059"
          android:type="linear">
        <item android:offset="0" android:color="#FFFFDA72"/>
        <item android:offset="1" android:color="#FFF7A967"/>
      </gradient>
    </aapt:attr>
  </path>
  <path
      android:pathData="M7.768,5.8163C7.7132,6.0293 7.5269,6.1882 7.3068,6.2983C6.6827,6.5142 6.1898,6.7219 5.7819,6.9236C5.4208,7.1021 5.4243,7.6662 5.7865,7.8423C6.2098,8.0481 6.7413,8.2454 7.3315,8.4794C7.4902,8.5423 7.7144,8.72 7.7703,8.9385C7.9423,9.6117 8.1763,10.3244 8.4341,10.9824C8.6342,11.4931 9.1288,11.4927 9.3298,10.9824C9.5908,10.3199 9.7891,9.6042 10.0129,8.9234C10.0665,8.7132 10.225,8.5469 10.4295,8.4745C10.9821,8.2787 11.5148,8.0578 11.9491,7.8665C12.3546,7.6879 12.3629,7.1081 11.9625,6.9184C11.5349,6.7158 11.003,6.4812 10.4268,6.2719C10.224,6.1982 10.068,6.0427 9.996,5.8219C9.7531,5.0781 9.5992,4.4475 9.3412,3.7927C9.1402,3.2823 8.6124,3.298 8.4113,3.8084C8.1543,4.4608 7.9748,5.1103 7.768,5.8163Z">
    <aapt:attr name="android:fillColor">
      <gradient 
          android:startY="11.9803"
          android:startX="8.8855"
          android:endY="7.85532"
          android:endX="8.8855"
          android:type="linear">
        <item android:offset="0" android:color="#FFFDA071"/>
        <item android:offset="1" android:color="#00FDA071"/>
      </gradient>
    </aapt:attr>
  </path>
  <path
      android:pathData="M5.226,20.0657C5.1495,20.3627 4.8899,20.5843 4.5829,20.7378C3.7126,21.0389 3.0252,21.3285 2.4564,21.6097C1.9529,21.8586 1.9578,22.6452 2.4629,22.8908C3.0532,23.1778 3.7942,23.453 4.6173,23.7792C4.8386,23.8669 5.1513,24.1148 5.2291,24.4194C5.469,25.3582 5.7954,26.3521 6.1548,27.2695C6.4338,27.9817 7.1236,27.9812 7.4039,27.2695C7.7678,26.3457 8.0443,25.3478 8.3564,24.3983C8.4311,24.1052 8.6522,23.8734 8.9373,23.7724C9.7079,23.4994 10.4508,23.1913 11.0563,22.9246C11.6217,22.6756 11.6334,21.867 11.075,21.6025C10.4788,21.32 9.7371,20.9929 8.9336,20.7009C8.6508,20.5982 8.4333,20.3813 8.3328,20.0735C7.9941,19.0363 7.7796,18.157 7.4198,17.2438C7.1394,16.5321 6.4034,16.554 6.1231,17.2657C5.7646,18.1755 5.5144,19.0811 5.226,20.0657Z">
    <aapt:attr name="android:fillColor">
      <gradient 
          android:gradientRadius="7.07598"
          android:centerX="10.0135"
          android:centerY="18.5671"
          android:type="radial">
        <item android:offset="0.364601" android:color="#FFFFBC64"/>
        <item android:offset="1" android:color="#FFFF8F6B"/>
      </gradient>
    </aapt:attr>
  </path>
</vector>
